pdb4ambermini/__init__.py
pdb4ambermini/pdb4amber.py
pdb4ambermini/residue.py
pdb4ambermini/utils.py
pdb4ambermini-0.1.3.dist-info/licenses/LICENSE
pdb4ambermini-0.1.3.dist-info/METADATA
pdb4ambermini-0.1.3.dist-info/WHEEL
pdb4ambermini-0.1.3.dist-info/entry_points.txt
pdb4ambermini-0.1.3.dist-info/top_level.txt
pdb4ambermini-0.1.3.dist-info/RECORD
