Metadata-Version: 2.4
Name: pdb4ambermini
Version: 0.1.3
Summary: Lightweight pdb4amber derivative without Amber binary dependencies
Author: pdb4ambermini contributors
License: MIT License
Classifier: License :: OSI Approved :: MIT License
Classifier: Programming Language :: Python :: 3
Classifier: Programming Language :: Python :: 3 :: Only
Classifier: Programming Language :: Python :: 3.8
Classifier: Programming Language :: Python :: 3.9
Classifier: Programming Language :: Python :: 3.10
Classifier: Programming Language :: Python :: 3.11
Classifier: Programming Language :: Python :: 3.12
Classifier: Topic :: Scientific/Engineering :: Chemistry
Requires-Python: >=3.8
License-File: LICENSE
Requires-Dist: numpy<2
Requires-Dist: parmed>=3.0
Dynamic: license-file
